AUTHORS.rst
HISTORY.rst
LICENSE.rst
MANIFEST.in
README.rst
requirements-dev.txt
requirements.txt
setup.py
click_captcha/__init__.py
click_captcha/apps.py
click_captcha/client_settings.py
click_captcha/fields.py
click_captcha/image_unicode.py
click_captcha/urls.py
click_captcha/views.py
click_captcha/widgets.py
click_captcha/static/click_captcha/css/bootstrap.min.css
click_captcha/static/click_captcha/css/click_captcha.css
click_captcha/static/click_captcha/fonts/glyphicons-halflings-regular.eot
click_captcha/static/click_captcha/fonts/glyphicons-halflings-regular.svg
click_captcha/static/click_captcha/fonts/glyphicons-halflings-regular.ttf
click_captcha/static/click_captcha/fonts/glyphicons-halflings-regular.woff
click_captcha/static/click_captcha/fonts/glyphicons-halflings-regular.woff2
click_captcha/static/click_captcha/js/click_captcha.js
click_captcha/static/click_captcha/js/jquery.js
click_captcha/templates/click_captcha/captcha.html
click_captcha/templates/click_captcha/css.html
click_captcha/templates/click_captcha/js.html
click_captcha/templatetags/__init__.py
click_captcha/templatetags/click_captcha_tags.py
django_click_captcha.egg-info/PKG-INFO
django_click_captcha.egg-info/SOURCES.txt
django_click_captcha.egg-info/dependency_links.txt
django_click_captcha.egg-info/not-zip-safe
django_click_captcha.egg-info/requires.txt
django_click_captcha.egg-info/top_level.txt
tests/__init__.py
tests/test_fields.py
tests/test_front_action.py
tests/test_image_unicode.py
tests/test_views.py
tests/test_widgets.py
tests/demo/__init__.py
tests/demo/apps.py
tests/demo/forms.py
tests/demo/settings.py
tests/demo/urls.py
tests/demo/views.py
tests/demo/wsgi.py
tests/demo/templates/index.html
tests/resource/Vera.ttf