Metadata-Version: 1.1
Name: django-click-captcha
Version: 0.1.1
Summary: Django 点击倒字验证码
Home-page: https://github.com/malongge/click_captcha.git
Author: 码龙哥
Author-email: ma_longge@sina.com
License: MIT
Keywords: django captcha
Platform: UNKNOWN
Classifier: Development Status :: 3 - Alpha
Classifier: Framework :: Django
Classifier: Intended Audience :: Developers
Classifier: Operating System :: OS Independent
Classifier: Programming Language :: Python
Classifier: Programming Language :: Python :: 3
Classifier: Topic :: Utilities
Classifier: Topic :: Internet :: WWW/HTTP
Classifier: License :: OSI Approved :: MIT License
